wirepas_mqtt_library/__about__.py
wirepas_mqtt_library/__init__.py
wirepas_mqtt_library/otap_status_storage.py
wirepas_mqtt_library/topic_helper.py
wirepas_mqtt_library/wirepas_network_interface.py
wirepas_mqtt_library/wirepas_otap_helper.py
wirepas_mqtt_library/wirepas_tlv_app_config_helper.py
wirepas_mqtt_library-1.2.6.dist-info/LICENSE
wirepas_mqtt_library-1.2.6.dist-info/METADATA
wirepas_mqtt_library-1.2.6.dist-info/WHEEL
wirepas_mqtt_library-1.2.6.dist-info/top_level.txt
wirepas_mqtt_library-1.2.6.dist-info/RECORD
