Metadata-Version: 2.1
Name: wirepas-mqtt-library
Version: 1.2.6
Summary: Library to interact with a Wirepas Network through MQTT/Protobuf API
Home-page: https://github.com/wirepas/wirepas-mqtt-library
Author: Wirepas Ltd
Author-email: opensource@wirepas.com
License: Apache-2
Keywords: wirepas connectivity iot mesh gateway backend
Platform: UNKNOWN
Classifier: Development Status :: 5 - Production/Stable
Classifier: Intended Audience :: Developers
Classifier: License :: OSI Approved :: Apache Software License
Classifier: Topic :: Software Development :: Libraries
Classifier: Programming Language :: Python :: 3
